nxelf/__init__.py
nxelf/elf.py
nxelf/macros.py
nxgdb/__init__.py
nxgdb/circbuf.py
nxgdb/debug.py
nxgdb/diagnose.py
nxgdb/dmesg.py
nxgdb/fs.py
nxgdb/gcore.py
nxgdb/irq.py
nxgdb/lists.py
nxgdb/memcheck.py
nxgdb/memdump.py
nxgdb/memleak.py
nxgdb/mm.py
nxgdb/net.py
nxgdb/prefix.py
nxgdb/profile.py
nxgdb/rpmsg.py
nxgdb/stack.py
nxgdb/thread.py
nxgdb/uorb.py
nxgdb/utils.py
nxgdb/wdog.py
nxgdb/wqueue.py
nxstub/__init__.py
nxstub/__main__.py
nxstub/gdbstub.py
nxstub/registers.py
nxstub/target.py
nxstub/utils.py
nxtrace/__init__.py
nxtrace/perfetto_trace.py
nxtrace/perfetto_trace_pb2.py
nxtrace/rtt.py
nxtrace/trace.py
pynuttxtest-0.0.1.1.dist-info/METADATA
pynuttxtest-0.0.1.1.dist-info/WHEEL
pynuttxtest-0.0.1.1.dist-info/entry_points.txt
pynuttxtest-0.0.1.1.dist-info/top_level.txt
pynuttxtest-0.0.1.1.dist-info/RECORD
